wcpy/__init__.py
wcpy/command_line.py
wcpy/mainwindow.py
wcpy/utils.py
wcpy/ui/__init__.py
wcpy/ui/fonts.py
wcpy/ui/mainwindow.py
wcpy/ui/widgets.py
wavelength_calibrator-0.0.6.3.dist-info/LICENSE
wavelength_calibrator-0.0.6.3.dist-info/METADATA
wavelength_calibrator-0.0.6.3.dist-info/WHEEL
wavelength_calibrator-0.0.6.3.dist-info/entry_points.txt
wavelength_calibrator-0.0.6.3.dist-info/top_level.txt
wavelength_calibrator-0.0.6.3.dist-info/RECORD
